vocabmaster/__init__.py
vocabmaster/cli.py
vocabmaster/config_handler.py
vocabmaster/csv_handler.py
vocabmaster/gpt_integration.py
vocabmaster/utils.py
vocabmaster-0.2.0.dist-info/licenses/LICENSE
vocabmaster-0.2.0.dist-info/METADATA
vocabmaster-0.2.0.dist-info/WHEEL
vocabmaster-0.2.0.dist-info/entry_points.txt
vocabmaster-0.2.0.dist-info/top_level.txt
vocabmaster-0.2.0.dist-info/RECORD
