Metadata-Version: 2.4
Name: VocabMaster
Version: 0.2.0
Home-page: https://github.com/sderev/vocabmaster
Author: Sébastien De Revière
License-File: LICENSE
Requires-Dist: click
Requires-Dist: openai<1.0
Requires-Dist: tiktoken
Dynamic: author
Dynamic: description
Dynamic: description-content-type
Dynamic: home-page
Dynamic: license-file
Dynamic: requires-dist
